joshk/__init__.py
joshk/__main__.py
joshk/funcs.py
joshk-0.1.3.dist-info/LICENSE
joshk-0.1.3.dist-info/WHEEL
joshk-0.1.3.dist-info/METADATA
joshk-0.1.3.dist-info/RECORD
